<tracks>
    <track>
        <name>Quasi Monza</name>
        <points>
            <p x="521" y="562"/>
            <p x="314" y="562"/>
            <p x="309" y="562"/>
            <p x="256" y="568"/>
            <p x="184" y="568"/>
            <p x="142" y="537"/>
            <p x="108" y="477"/>
            <p x="75" y="250"/>
            <p x="60" y="234"/>
            <p x="17" y="90"/>
            <p x="19" y="61"/>
            <p x="36" y="44"/>
            <p x="108" y="26"/>
            <p x="207" y="187"/>
            <p x="361" y="400"/>
            <p x="396" y="400"/>
            <p x="424" y="425"/>
            <p x="745" y="431"/>
            <p x="773" y="448"/>
            <p x="778" y="481"/>
            <p x="769" y="512"/>
            <p x="748" y="537"/>
            <p x="711" y="552"/>
            <p x="623" y="562"/>
            <p x="521" y="562"/>  <!-- Repeat first point to close the curve. -->
        </points>
    </track>
    <track>
        <name>Anello tipo Nardo</name>
        <points>
            <p y="1000" x="2000"/>
            <p y="1099,8334166468" x="1995,004165278"/>
            <p y="1198,6693307951" x="1980,0665778413"/>
            <p y="1295,5202066613" x="1955,3364891256"/>
            <p y="1389,4183423087" x="1921,0609940029"/>
            <p y="1479,4255386042" x="1877,5825618904"/>
            <p y="1564,642473395" x="1825,3356149097"/>
            <p y="1644,2176872377" x="1764,8421872845"/>
            <p y="1717,3560908995" x="1696,7067093472"/>
            <p y="1783,3269096275" x="1621,6099682707"/>
            <p y="1841,4709848079" x="1540,3023058681"/>
            <p y="1891,2073600614" x="1453,5961214256"/>
            <p y="1932,0390859672" x="1362,3577544767"/>
            <p y="1963,5581854172" x="1267,4988286246"/>
            <p y="1985,4497299885" x="1169,9671429002"/>
            <p y="1997,4949866041" x="1070,7372016677"/>
            <p y="1999,5736030415" x="970,8004776987"/>
            <p y="1991,6648104525" x="871,1555057045"/>
            <p y="1973,8476308782" x="772,7979053069"/>
            <p y="1946,3000876874" x="676,7104331365"/>
            <p y="1909,2974268257" x="583,8531634529"/>
            <p y="1863,2093666489" x="495,1538954001"/>
            <p y="1808,4964038196" x="411,4988827447"/>
            <p y="1745,7052121767" x="333,7239787202"/>
            <p y="1675,4631805512" x="262,6062844588"/>
            <p y="1598,472144104" x="198,8563844531"/>
            <p y="1515,5013718215" x="143,1112466311"/>
            <p y="1427,3798802338" x="95,9278579829"/>
            <p y="1334,9881501559" x="57,7776593313"/>
            <p y="1239,249329214" x="29,0418348504"/>
            <p y="1141,1200080599" x="10,0075033996"/>
            <p y="1041,5806624333" x="0,8648497267"/>
            <p y="941,6258565724" x="1,7052242052"/>
            <p y="842,2543058568" x="12,5202300911"/>
            <p y="744,4588979732" x="33,2018074205"/>
            <p y="649,2167723104" x="63,5433127092"/>
            <p y="557,4795567051" x="103,2415836659"/>
            <p y="470,1638590915" x="151,8999682896"/>
            <p y="388,1421090573" x="209,0322880856"/>
            <p y="312,233840816" x="274,0676957999"/>
            <p y="243,1975046921" x="346,3563791364"/>
            <p y="181,7228889356" x="425,1760534667"/>
            <p y="128,4242275864" x="509,7391786593"/>
            <p y="83,8340632505" x="599,20082792"/>
            <p y="48,3979261105" x="692,6671300216"/>
            <p y="22,4698823349" x="789,2042005692"/>
            <p y="6,3089963665" x="887,8474730649"/>
            <p y="0,0767424359" x="987,6113365371"/>
            <p y="3,8353911642" x="1087,4989834395"/>
            <p y="17,5473873757" x="1186,5123694226"/>
            <p y="41,0757253369" x="1283,6621854632"/>
            <p y="74,1853176723" x="1377,977742713"/>
            <p y="116,5453442798" x="1468,5166713004"/>
            <p y="167,7325577761" x="1554,3743361792"/>
            <p y="227,235512444" x="1634,6928759426"/>
            <p y="294,4596744296" x="1708,6697742913"/>
            <p y="368,7333621277" x="1775,5658785103"/>
            <p y="449,3144574024" x="1834,7127848392"/>
            <p y="535,3978205862" x="1885,5195169413"/>
            <p y="626,1233351698" x="1927,478430744"/>
            <p y="720,5845018011" x="1960,1702866504"/>
            <p y="817,8374957279" x="1983,2684384426"/>
            <p y="916,9105971825" x="1996,5420970232"/>
            <p y="996,8146982069" x="1999,9949269134"/>
        </points>
    </track>
</tracks>